MANIFEST.in
README.rst
setup.py
pyzpl2.egg-info/PKG-INFO
pyzpl2.egg-info/SOURCES.txt
pyzpl2.egg-info/dependency_links.txt
pyzpl2.egg-info/requires.txt
pyzpl2.egg-info/top_level.txt
tests/__init__.py
tests/testZpl2.py
zpl2/__init__.py
zpl2/zpl2.py