Metadata-Version: 1.1
Name: pyzpl2
Version: 0.1
Summary: ZPL II
Home-page: https://github.com/twam/pyzpl2
Author: Tobias Müller
Author-email: Tobias_Mueller@twam.info
License: MIT
Keywords: zebra zpl zpl2 zplII label
Platform: any
Classifier: Development Status :: 3 - Alpha
Classifier: Intended Audience :: Developers
Classifier: License :: OSI Approved :: MIT License
Classifier: Natural Language :: English
Classifier: Operating System :: POSIX
Classifier: Operating System :: Microsoft :: Windows
Classifier: Operating System :: MacOS :: MacOS X
Classifier: Programming Language :: Python :: 3.3
Classifier: Programming Language :: Python :: 3.4
Classifier: Programming Language :: Python :: 3.5
Classifier: Topic :: Printing
